Workbook

Sheet Diagrama ER (corregido)
A1: Diagrama Entidad-Relación (Chen) corregido - Red Social Pascualina
A2: Rectángulo = entidad; rectángulo doble = entidad débil; rombo = relación (verbo en 3a persona); rombo doble = relación identificadora. Cardinalidades 1:1, 1:N y N:M sobre cada línea.

Sheet Inventario Modelo Lógico (corre
A1: Tablas resultantes del Diccionario Genérico (Modelo Lógico)
A2: # | B2: Tabla | C2: Descripción Tabla | D2: Observaciones
A3: 1 | B3: rol | C3: Catálogo de niveles de permiso con que un usuario opera en la Red (administrador, auxiliar, miembro, visitante). | D3: Entidad. Catálogo independiente. Se elimina el FK a usuario para evitar referencia circular.
A4: =A3+1 | B4: tipo_usuario | C4: Catálogo del vínculo del usuario con la Institución (estudiante, docente, egresado, empleado, empresario). | D4: Entidad. Catálogo independiente. Se elimina id_usuario_registra (referencia circular con usuario).
A5: =A4+1 | B5: usuario | C5: Persona registrada en la Red Social Pascualina; eje de toda la actividad de la plataforma. | D5: Entidad. Absorbe las relaciones N:1 'tiene rol' y 'tiene tipo' como FK. Se eliminan usuario_tiene_rol y usuario_tiene_tipo.
A6: =A5+1 | B6: cuenta | C6: Credenciales y estado de acceso del usuario, separadas de sus datos personales. | D6: Entidad débil (1:1). PK = FK a usuario. Se elimina usuario_tiene_cuenta (duplicaba la relación 1:1).
A7: =A6+1 | B7: grupo | C7: Comunidad de usuarios reunida por un interés común: grupos de estudio, semilleros, hackatones, clubes. | D7: Entidad. Se agregan es_privado y estado_grupo del modelo conceptual.
A8: =A7+1 | B8: perfil | C8: Información pública e intereses de un usuario o de un grupo; incluye atributos semiestructurados JSONB. | D8: Entidad. Absorbe cuenta_tiene_perfil y grupo_define_perfil. CHECK de exclusividad usuario/grupo.
A9: =A8+1 | B9: grupo_usuario | C9: Membresía de usuarios en grupos (N:M), con estado de solicitud y rol dentro del grupo. | D9: Relación N:M. Absorbe usuario_solicita_grupo y usuario_administra_grupo (estado_membresia y rol_en_grupo).
A10: =A9+1 | B10: usuario_sigue_usuario | C10: Relación recursiva de seguimiento entre usuarios (seguidor -> seguido). | D10: Relación N:M recursiva. Nueva exigencia de la EA3: conectar y seguir compañeros.
A11: =A10+1 | B11: publicacion | C11: Contenido que un usuario comparte en la Red, opcionalmente dentro de un grupo. | D11: Entidad. Absorbe usuario_realiza_publicacion (era la misma tabla duplicada).
A12: =A11+1 | B12: comentario | C12: Respuesta que un usuario escribe sobre una publicación; el autor puede ser distinto al de la publicación. | D12: Entidad. Absorbe publicacion_tiene_comentario y usuario_comenta.
A13: =A12+1 | B13: reaccion | C13: Reacción breve (me gusta, me encanta...) de un usuario a una publicación; una sola por usuario y publicación. | D13: Entidad débil. PK compuesta (id_publicacion, id_usuario). Absorbe publicacion_tiene_reaccion y usuario_reacciona.
A14: =A13+1 | B14: mensaje | C14: Mensaje privado enviado por un usuario a otro dentro de la plataforma. | D14: Entidad. Absorbe usuario_envia_mensaje y usuario_recibe_mensaje.
A15: =A14+1 | B15: notificacion | C15: Aviso generado por el sistema y dirigido a un usuario sobre la actividad que le concierne. | D15: Entidad. Absorbe usuario_recibe_notificacion.
... A25: =A24+1 | B25: participacion_evento | C25: Inscripción de usuarios a eventos: traza de pago, asistencia, me gusta y comentario posterior. | D25: Relación N:M con atributos. Implementa la relación 'participa' y la traza de ventas de eventos.

Sheet Trazabilidad EA2-EA3
A1: Trazabilidad: destino de las 46 tablas del modelo lógico anterior (EA2) en el modelo corregido (EA3)
A2: # EA2 | B2: Tabla EA2 | C2: Destino en EA3 | D2: Cómo / por qué
A3: 1 | B3: usuario | C3: usuario | D3: Se conserva (entidad).
A4: 2 | B4: rol | C4: rol | D4: Se conserva (catálogo).
A5: 3 | B5: tipo_usuario | C5: tipo_usuario | D5: Se conserva; se quita id_usuario_registra (ciclo con usuario).
A6: 4 | B6: cuenta | C6: cuenta | D6: Se conserva; PK = FK id_usuario.
A7: 5 | B7: perfil | C7: perfil | D7: Se conserva; recupera los atributos de la EA1 (area_estudio, atributos_perfil JSONB).
A8: 6 | B8: grupo | C8: grupo | D8: Se conserva.
A9: 7 | B9: mensaje | C9: mensaje | D9: Se conserva; recibe las FK de remitente y destinatario.
A10: 8 | B10: publicacion | C10: publicacion | D10: Se conserva.
A11: 9 | B11: comentario | C11: comentario | D11: Se conserva.
A12: 10 | B12: reaccion | C12: reaccion | D12: Se conserva; PK compuesta (id_publicacion, id_usuario).
A13: 11 | B13: notificacion | C13: notificacion | D13: Se conserva.
A14: 12 | B14: tipo_servicio | C14: tipo_servicio | D14: Se conserva.
... A48: 46 | B48: usuario_organiza_evento | C48: evento.id_usuario_organizador | D48: 1:N → FK; repetía título, fecha y lugar.
A50: Tablas recuperadas del modelo conceptual (EA1) que la EA2 había omitido
A51: nueva | B51: — | C51: solicitud_servicio | D51: Relación N:M "solicita" del modelo conceptual (EA1) que la EA2 había omitido. Traza de servicios (EA3).
A52: nueva | B52: — | C52: compra_producto | D52: Relación N:M "compra" del modelo conceptual (EA1) que la EA2 había omitido. Traza de ventas (EA3).
A53: nueva | B53: — | C53: participacion_evento | D53: Relación N:M "participa" del modelo conceptual (EA1) que la EA2 había omitido. Traza de eventos (EA3).

Sheet Tipos de Dato
A1: Tipos de Datos - Tabla Comparativa
A2: # | B2: Tipo de Dato Genérico | C2: Tipos de Dato - PosgreSQL | D2: Dominio | E2: Tamaño BYTES | F2: Observaciones
A3: 1 | B3: AUTOINCREMENTABLE | C3: SMALLINT / INTEGER / BIGINT GENERATED ALWAYS AS IDENTITY | D3: Enteros 1 .. 32.767 / 2.147.483.647 / 9,2x10^18 | E3: 2 / 4 / 8 | F3: Estándar SQL. Reemplaza SERIAL. Usado en todas las PK sustitutas (id_usuario INTEGER, id_publicacion BIGINT).
A4: =A3+1 | B4: UUID | C4: UUID | D4: 128 bits, ej. a0eebc99-9c0b-4ef8-bb6d-6bb9bd380a11 | E4: 16 | F4: Disponible con gen_random_uuid(). No se usa en el modelo: las PK enteras (4 bytes) son suficientes y ocupan menos espacio.
A5: =A4+1 | B5: ENTERO | C5: SMALLINT / INTEGER / BIGINT | D5: -32.768..32.767 / ±2.147 millones / ±9,2x10^18 | E5: 2 / 4 / 8 | F5: SMALLINT para catálogos y puntuación; INTEGER para cantidades y cupos; BIGINT para tablas de alto volumen.
A6: =A5+1 | B6: DECIMAL | C6: NUMERIC(p,s) | D6: Hasta 131.072 dígitos antes del punto; exacto | E6: Variable (≈ 2 por cada 4 dígitos + 3-8) | F6: NUMERIC(12,2) para precios y valores en pesos: exacto, sin errores de redondeo de REAL/DOUBLE.
A7: =A6+1 | B7: LÓGICO | C7: BOOLEAN | D7: TRUE / FALSE / NULL | E7: 1 | F7: Todo atributo de dos valores: es_privado, fue_leido, asistio, es_nuevo, estado_rol.
A8: =A7+1 | B8: TEXTO | C8: TEXT / VARCHAR(n) | D8: Cadena de longitud variable (hasta 1 GB) | E8: Variable (n + 1 a 4) | F8: TEXT para contenido largo sin tope (publicaciones, mensajes); VARCHAR(n) cuando el negocio fija un máximo.
A9: =A8+1 | B9: CARACTER | C9: CHAR(n) / VARCHAR(n) | D9: Cadena de longitud fija (CHAR) o limitada (VARCHAR) | E9: n + 1 | F9: Se prefiere VARCHAR(n) para códigos y estados cortos: CHAR rellena con espacios.
A10: =A9+1 | B10: FECHA | C10: DATE | D10: 4713 a.C. .. 5874897 d.C., resolución 1 día | E10: 4 | F10: fecha_nacimiento, fecha_creacion del grupo.
A11: =A10+1 | B11: FECHA_HORA | C11: TIMESTAMP | D11: 4713 a.C. .. 294276 d.C., resolución 1 µs | E11: 8 | F11: Trazabilidad: fecha_publicacion, fecha_compra, fecha_envio. DEFAULT CURRENT_TIMESTAMP.
A12: =A11+1 | B12: IMAGEN | C12: VARCHAR(255) (URL) / BYTEA | D12: Ruta o enlace a la imagen / binario | E12: Variable | F12: Se guarda la URL (url_fotografia, url_multimedia) y el archivo en almacenamiento externo; BYTEA engorda la BD.
A13: =A12+1 | B13: AUDIO | C13: VARCHAR(255) (URL) / BYTEA | D13: Ruta o enlace al audio / binario | E13: Variable | F13: Mismo criterio que IMAGEN (no usado en el modelo actual).
A14: =A13+1 | B14: URL | C14: VARCHAR(255) | D14: Cadena hasta 255 caracteres | E14: Hasta 256 | F14: url_multimedia, url_fotografia.
A15: =A14+1 | B15: ENUM | C15: VARCHAR(n) + CHECK (campo IN (...)) | D15: Conjunto cerrado de valores | E15: Variable | F15: Se usa CHECK en lugar de CREATE TYPE ... AS ENUM porque agregar valores es más simple con ALTER TABLE.
... A18: =A17+1 | B18: JSON | C18: JSONB | D18: Documento JSON almacenado en binario | E18: Variable | F18: perfil.atributos_perfil (intereses, habilidades, deportes). JSONB permite índices GIN y consultas por clave.

Sheet DICCIONARIO DATOS (Físico)
A1: DICCIONARIO DE DATOS FÍSICO (PostgreSQL)
A2: Inventario de Tablas
A3: # | B3: Tabla | F3: Descripción Tabla | X3: Observaciones
A4: 1 | B4: ='Inventario Modelo Lógico (corre'!B3 | F4: ='Inventario Modelo Lógico (corre'!C3 | X4: Entidad
A5: =A4+1 | B5: ='Inventario Modelo Lógico (corre'!B4 | F5: ='Inventario Modelo Lógico (corre'!C4 | X5: Entidad
A6: =A5+1 | B6: ='Inventario Modelo Lógico (corre'!B5 | F6: ='Inventario Modelo Lógico (corre'!C5 | X6: Entidad
A7: =A6+1 | B7: ='Inventario Modelo Lógico (corre'!B6 | F7: ='Inventario Modelo Lógico (corre'!C6 | X7: Entidad débil (1:1)
A8: =A7+1 | B8: ='Inventario Modelo Lógico (corre'!B7 | F8: ='Inventario Modelo Lógico (corre'!C7 | X8: Entidad
A9: =A8+1 | B9: ='Inventario Modelo Lógico (corre'!B8 | F9: ='Inventario Modelo Lógico (corre'!C8 | X9: Entidad
A10: =A9+1 | B10: ='Inventario Modelo Lógico (corre'!B9 | F10: ='Inventario Modelo Lógico (corre'!C9 | X10: Relación N:M
A11: =A10+1 | B11: ='Inventario Modelo Lógico (corre'!B10 | F11: ='Inventario Modelo Lógico (corre'!C10 | X11: Relación N:M recursiva
A12: =A11+1 | B12: ='Inventario Modelo Lógico (corre'!B11 | F12: ='Inventario Modelo Lógico (corre'!C11 | X12: Entidad
A13: =A12+1 | B13: ='Inventario Modelo Lógico (corre'!B12 | F13: ='Inventario Modelo Lógico (corre'!C12 | X13: Entidad
A14: =A13+1 | B14: ='Inventario Modelo Lógico (corre'!B13 | F14: ='Inventario Modelo Lógico (corre'!C13 | X14: Entidad débil
A15: =A14+1 | B15: ='Inventario Modelo Lógico (corre'!B14 | F15: ='Inventario Modelo Lógico (corre'!C14 | X15: Entidad
A16: =A15+1 | B16: ='Inventario Modelo Lógico (corre'!B15 | F16: ='Inventario Modelo Lógico (corre'!C15 | X16: Entidad
... A26: =A25+1 | B26: ='Inventario Modelo Lógico (corre'!B25 | F26: ='Inventario Modelo Lógico (corre'!C25 | X26: Relación N:M con atributos
A30: Tablas en Detalle
A32: 1 | B32: Tabla | C32: =B4 | G32: Descripción Tabla | K32: =F4 | X32: Versión | Y32: 3.0
A33: # | B33: Campo | C33: Descripción Campo | G33: Tipo Dato (PostgreSQL) | K33: Tamaño / Longitud | O33: Nulo | R33: PK | T33: FK | V33: UK | X33: Nota/Comentarios
A34: 1 | B34: id_rol | C34: Identificador único del rol | G34: SMALLINT | K34: 2 bytes | O34: No | R34: S | X34: GENERATED ALWAYS AS IDENTITY
A35: 2 | B35: nombre_rol | C35: Nombre del rol: administrador, auxiliar, miembro, visitante | G35: VARCHAR | K35: 30 | O35: No | V35: S
A36: 3 | B36: descripcion_rol | C36: Alcance de los permisos que otorga el rol | G36: VARCHAR | K36: 255 | O36: Sí
A37: 4 | B37: estado_rol | C37: Indica si el rol puede asignarse (TRUE = vigente) | G37: BOOLEAN | K37: 1 byte | O37: No | X37: DEFAULT true
A40: 2 | B40: Tabla | C40: =B5 | G40: Descripción Tabla | K40: =F5 | X40: Versión | Y40: 3.0
A41: # | B41: Campo | C41: Descripción Campo | G41: Tipo Dato (PostgreSQL) | K41: Tamaño / Longitud | O41: Nulo | R41: PK | T41: FK | V41: UK | X41: Nota/Comentarios
A42: 1 | B42: id_tipo_usuario | C42: Identificador único del tipo de usuario | G42: SMALLINT | K42: 2 bytes | O42: No | R42: S | X42: GENERATED ALWAYS AS IDENTITY
A43: 2 | B43: nombre_tipo_usuario | C43: Nombre del tipo: estudiante, docente, egresado... | G43: VARCHAR | K43: 40 | O43: No | V43: S
A44: 3 | B44: descripcion_tipo_usuario | C44: Aclaración del alcance del tipo de usuario | G44: VARCHAR | K44: 255 | O44: Sí
A45: 4 | B45: estado_tipo_usuario | C45: Indica si el tipo está vigente para nuevas asignaciones | G45: BOOLEAN | K45: 1 byte | O45: No | X45: DEFAULT true
A48: 3 | B48: Tabla | C48: =B6 | G48: Descripción Tabla | K48: =F6 | X48: Versión | Y48: 3.0
A49: # | B49: Campo | C49: Descripción Campo | G49: Tipo Dato (PostgreSQL) | K49: Tamaño / Longitud | O49: Nulo | R49: PK | T49: FK | V49: UK | X49: Nota/Comentarios
A50: 1 | B50: id_usuario | C50: Identificador interno del usuario | G50: INTEGER | K50: 4 bytes | O50: No | R50: S | X50: GENERATED ALWAYS AS IDENTITY
A51: 2 | B51: id_tipo_usuario | C51: Tipo de usuario (vínculo con la Institución) | G51: SMALLINT | K51: 2 bytes | O51: No | T51: S | X51: Ref. tipo_usuario(id_tipo_usuario) ON DELETE RESTRICT ON UPDATE CASCADE
A52: 3 | B52: id_rol | C52: Rol de permisos en la Red | G52: SMALLINT | K52: 2 bytes | O52: No | T52: S | X52: Ref. rol(id_rol) ON DELETE RESTRICT ON UPDATE CASCADE
A53: 4 | B53: numero_documento | C53: Documento de identidad | G53: VARCHAR | K53: 20 | O53: No | V53: S
A54: 5 | B54: nombres_usuario | C54: Nombres de la persona | G54: VARCHAR | K54: 60 | O54: No
A55: 6 | B55: apellidos_usuario | C55: Apellidos de la persona | G55: VARCHAR | K55: 60 | O55: No
A56: 7 | B56: correo_electronico | C56: Correo de contacto, no repetible | G56: VARCHAR | K56: 120 | O56: No | V56: S | X56: CHECK (correo_electronico)~~ '%_@_%._%')
A57: 8 | B57: telefono_usuario | C57: Teléfono de contacto | G57: VARCHAR | K57: 15 | O57: Sí
A58: 9 | B58: fecha_nacimiento | C58: Fecha de nacimiento (análisis demográfico) | G58: DATE | K58: 4 bytes | O58: Sí | X58: CHECK (fecha_nacimiento < CURRENT_DATE)
A59: 10 | B59: fecha_registro | C59: Fecha y hora de registro en la Red | G59: TIMESTAMP | K59: 8 bytes | O59: No | X59: DEFAULT CURRENT_TIMESTAMP
A60: 11 | B60: estado_usuario | C60: Estado: activo, inactivo o suspendido | G60: VARCHAR | K60: 12 | O60: No | X60: DEFAULT 'activo'; CHECK (estado_usuario)IN ('activo', 'inactivo', 'suspendido')
A63: 4 | B63: Tabla | C63: =B7 | G63: Descripción Tabla | K63: =F7 | X63: Versión | Y63: 3.0
A64: # | B64: Campo | C64: Descripción Campo | G64: Tipo Dato (PostgreSQL) | K64: Tamaño / Longitud | O64: Nulo | R64: PK | T64: FK | V64: UK | X64: Nota/Comentarios
A65: 1 | B65: id_usuario | C65: Usuario dueño de la cuenta (PK y FK, relación 1:1) | G65: INTEGER | K65: 4 bytes | O65: No | R65: S | T65: S | X65: Ref. usuario(id_usuario) ON DELETE CASCADE ON UPDATE CASCADE
A66: 2 | B66: nombre_cuenta | C66: Nombre de usuario para iniciar sesión | G66: VARCHAR | K66: 30 | O66: No | V66: S
A67: 3 | B67: clave_cifrada | C67: Hash de la contraseña (nunca texto plano) | G67: VARCHAR | K67: 255 | O67: No
A68: 4 | B68: estado_cuenta | C68: Estado: activa, bloqueada o pendiente | G68: VARCHAR | K68: 12 | O68: No | X68: DEFAULT 'pendiente'; CHECK (estado_cuenta)IN ('activa', 'bloqueada', 'pendiente')
A69: 5 | B69: fecha_ultimo_acceso | C69: Fecha y hora del último ingreso exitoso | G69: TIMESTAMP | K69: 8 bytes | O69: Sí
A70: 6 | B70: intentos_fallidos | C70: Intentos fallidos consecutivos de acceso | G70: SMALLINT | K70: 2 bytes | O70: No | X70: DEFAULT 0; CHECK (intentos_fallidos >= 0)
A73: 5 | B73: Tabla | C73: =B8 | G73: Descripción Tabla | K73: =F8 | X73: Versión | Y73: 3.0
A74: # | B74: Campo | C74: Descripción Campo | G74: Tipo Dato (PostgreSQL) | K74: Tamaño / Longitud | O74: Nulo | R74: PK | T74: FK | V74: UK | X74: Nota/Comentarios
A75: 1 | B75: id_grupo | C75: Identificador único del grupo | G75: INTEGER | K75: 4 bytes | O75: No | R75: S | X75: GENERATED ALWAYS AS IDENTITY
A76: 2 | B76: nombre_grupo | C76: Nombre del grupo, no repetible | G76: VARCHAR | K76: 80 | O76: No | V76: S
A77: 3 | B77: descripcion_grupo | C77: Propósito e intereses del grupo | G77: VARCHAR | K77: 500 | O77: Sí
A78: 4 | B78: fecha_creacion | C78: Fecha de creación del grupo | G78: DATE | K78: 4 bytes | O78: No | X78: DEFAULT CURRENT_DATE
A79: 5 | B79: es_privado | C79: TRUE si el ingreso requiere aprobación | G79: BOOLEAN | K79: 1 byte | O79: No | X79: DEFAULT false
A80: 6 | B80: estado_grupo | C80: Estado: activo, inactivo o cerrado | G80: VARCHAR | K80: 10 | O80: No | X80: DEFAULT 'activo'; CHECK (estado_grupo)IN ('activo', 'inactivo', 'cerrado')
A83: 6 | B83: Tabla | C83: =B9 | G83: Descripción Tabla | K83: =F9 | X83: Versión | Y83: 3.0
A84: # | B84: Campo | C84: Descripción Campo | G84: Tipo Dato (PostgreSQL) | K84: Tamaño / Longitud | O84: Nulo | R84: PK | T84: FK | V84: UK | X84: Nota/Comentarios
A85: 1 | B85: id_perfil | C85: Identificador único del perfil | G85: INTEGER | K85: 4 bytes | O85: No | R85: S | X85: GENERATED ALWAYS AS IDENTITY
A86: 2 | B86: id_usuario | C86: Usuario dueño del perfil (vacío si es de grupo) | G86: INTEGER | K86: 4 bytes | O86: Sí | T86: S | V86: S | X86: Ref. usuario(id_usuario) ON DELETE CASCADE ON UPDATE CASCADE; CHECK (id_usuario IS NOT NULL) AND (id_grupo IS NULL) OR (id_usuario IS NULL) AND (id_grupo IS NOT NULL)
A87: 3 | B87: id_grupo | C87: Grupo dueño del perfil (vacío si es de usuario) | G87: INTEGER | K87: 4 bytes | O87: Sí | T87: S | V87: S | X87: Ref. grupo(id_grupo) ON DELETE CASCADE ON UPDATE CASCADE; CHECK (id_usuario IS NOT NULL) AND (id_grupo IS NULL) OR (id_usuario IS NULL) AND (id_grupo IS NOT NULL)
A88: 4 | B88: titular_perfil | C88: Título visible del perfil | G88: VARCHAR | K88: 100 | O88: No
A89: 5 | B89: area_estudio | C89: Área de estudio o disciplina principal | G89: VARCHAR | K89: 100 | O89: Sí
A90: 6 | B90: descripcion_perfil | C90: Presentación breve del titular | G90: VARCHAR | K90: 500 | O90: Sí
A91: 7 | B91: atributos_perfil | C91: Intereses, habilidades, deportes, libros (JSONB) | G91: JSONB | K91: Variable | O91: Sí
A92: 8 | B92: url_fotografia | C92: Enlace a la foto de perfil | G92: VARCHAR | K92: 255 | O92: Sí
A93: 9 | B93: fecha_actualizacion | C93: Fecha y hora de la última modificación | G93: TIMESTAMP | K93: 8 bytes | O93: No | X93: DEFAULT CURRENT_TIMESTAMP
A96: 7 | B96: Tabla | C96: =B10 | G96: Descripción Tabla | K96: =F10 | X96: Versión | Y96: 3.0
A97: # | B97: Campo | C97: Descripción Campo | G97: Tipo Dato (PostgreSQL) | K97: Tamaño / Longitud | O97: Nulo | R97: PK | T97: FK | V97: UK | X97: Nota/Comentarios
A98: 1 | B98: id_grupo | C98: Grupo al que pertenece (parte de la PK) | G98: INTEGER | K98: 4 bytes | O98: No | R98: S | T98: S | X98: Ref. grupo(id_grupo) ON DELETE CASCADE ON UPDATE CASCADE
A99: 2 | B99: id_usuario | C99: Usuario miembro (parte de la PK) | G99: INTEGER | K99: 4 bytes | O99: No | R99: S | T99: S | X99: Ref. usuario(id_usuario) ON DELETE CASCADE ON UPDATE CASCADE
A100: 3 | B100: fecha_ingreso | C100: Fecha y hora de solicitud/ingreso | G100: TIMESTAMP | K100: 8 bytes | O100: No | X100: DEFAULT CURRENT_TIMESTAMP
A101: 4 | B101: estado_membresia | C101: Estado: pendiente, activa, rechazada, retirada | G101: VARCHAR | K101: 12 | O101: No | X101: DEFAULT 'pendiente'; CHECK (estado_membresia)IN ('pendiente', 'activa', 'rechazada', 'retirada')
A102: 5 | B102: rol_en_grupo | C102: Rol interno: administrador, moderador, miembro | G102: VARCHAR | K102: 15 | O102: No | X102: DEFAULT 'miembro'; CHECK (rol_en_grupo)IN ('administrador', 'moderador', 'miembro')
A105: 8 | B105: Tabla | C105: =B11 | G105: Descripción Tabla | K105: =F11 | X105: Versión | Y105: 3.0
A106: # | B106: Campo | C106: Descripción Campo | G106: Tipo Dato (PostgreSQL) | K106: Tamaño / Longitud | O106: Nulo | R106: PK | T106: FK | V106: UK | X106: Nota/Comentarios
A107: 1 | B107: id_usuario_seguidor | C107: Usuario que sigue (parte de la PK) | G107: INTEGER | K107: 4 bytes | O107: No | R107: S | T107: S | X107: Ref. usuario(id_usuario) ON DELETE CASCADE ON UPDATE CASCADE; CHECK (id_usuario_seguidor <> id_usuario_seguido)
A108: 2 | B108: id_usuario_seguido | C108: Usuario seguido (parte de la PK) | G108: INTEGER | K108: 4 bytes | O108: No | R108: S | T108: S | X108: Ref. usuario(id_usuario) ON DELETE CASCADE ON UPDATE CASCADE; CHECK (id_usuario_seguidor <> id_usuario_seguido)
A109: 3 | B109: fecha_seguimiento | C109: Fecha y hora en que empezó a seguir | G109: TIMESTAMP | K109: 8 bytes | O109: No | X109: DEFAULT CURRENT_TIMESTAMP
A112: 9 | B112: Tabla | C112: =B12 | G112: Descripción Tabla | K112: =F12 | X112: Versión | Y112: 3.0
A113: # | B113: Campo | C113: Descripción Campo | G113: Tipo Dato (PostgreSQL) | K113: Tamaño / Longitud | O113: Nulo | R113: PK | T113: FK | V113: UK | X113: Nota/Comentarios
A114: 1 | B114: id_publicacion | C114: Identificador único de la publicación | G114: BIGINT | K114: 8 bytes | O114: No | R114: S | X114: GENERATED ALWAYS AS IDENTITY
A115: 2 | B115: id_usuario | C115: Usuario autor | G115: INTEGER | K115: 4 bytes | O115: No | T115: S | X115: Ref. usuario(id_usuario) ON DELETE RESTRICT ON UPDATE CASCADE
A116: 3 | B116: id_grupo | C116: Grupo donde se publica (vacío = muro general) | G116: INTEGER | K116: 4 bytes | O116: Sí | T116: S | X116: Ref. grupo(id_grupo) ON DELETE SET NULL ON UPDATE CASCADE
A117: 4 | B117: titulo_publicacion | C117: Encabezado corto | G117: VARCHAR | K117: 150 | O117: Sí
A118: 5 | B118: contenido_publicacion | C118: Texto completo de la publicación | G118: TEXT | K118: Variable | O118: No
A119: 6 | B119: url_multimedia | C119: Enlace al archivo adjunto (imagen o video) | G119: VARCHAR | K119: 255 | O119: Sí
A120: 7 | B120: fecha_publicacion | C120: Fecha y hora de publicación | G120: TIMESTAMP | K120: 8 bytes | O120: No | X120: DEFAULT CURRENT_TIMESTAMP
A121: 8 | B121: estado_publicacion | C121: Estado: visible, oculto, eliminado | G121: VARCHAR | K121: 10 | O121: No | X121: DEFAULT 'visible'; CHECK (estado_publicacion)IN ('visible', 'oculto', 'eliminado')
A124: 10 | B124: Tabla | C124: =B13 | G124: Descripción Tabla | K124: =F13 | X124: Versión | Y124: 3.0
A125: # | B125: Campo | C125: Descripción Campo | G125: Tipo Dato (PostgreSQL) | K125: Tamaño / Longitud | O125: Nulo | R125: PK | T125: FK | V125: UK | X125: Nota/Comentarios
A126: 1 | B126: id_comentario | C126: Identificador único del comentario | G126: BIGINT | K126: 8 bytes | O126: No | R126: S | X126: GENERATED ALWAYS AS IDENTITY
A127: 2 | B127: id_publicacion | C127: Publicación comentada | G127: BIGINT | K127: 8 bytes | O127: No | T127: S | X127: Ref. publicacion(id_publicacion) ON DELETE CASCADE ON UPDATE CASCADE
A128: 3 | B128: id_usuario | C128: Usuario que comenta | G128: INTEGER | K128: 4 bytes | O128: No | T128: S | X128: Ref. usuario(id_usuario) ON DELETE RESTRICT ON UPDATE CASCADE
A129: 4 | B129: texto_comentario | C129: Texto del comentario | G129: VARCHAR | K129: 1000 | O129: No
A130: 5 | B130: fecha_comentario | C130: Fecha y hora del comentario | G130: TIMESTAMP | K130: 8 bytes | O130: No | X130: DEFAULT CURRENT_TIMESTAMP
A131: 6 | B131: estado_comentario | C131: Estado: visible, oculto, eliminado | G131: VARCHAR | K131: 10 | O131: No | X131: DEFAULT 'visible'; CHECK (estado_comentario)IN ('visible', 'oculto', 'eliminado')
...
